Metadata-Version: 2.1
Name: tesseractpy
Version: 1.0.0
Summary: tesseractpy - Tesseract C# wrapper wrapped in Python
Author: LUA9
Maintainer: LUA9
License: UNKNOWN
Platform: UNKNOWN
